lclpy/__init__.py
lclpy/aidfunc/__init__.py
lclpy/aidfunc/add_to_data_func.py
lclpy/aidfunc/convert_data.py
lclpy/aidfunc/error_func.py
lclpy/aidfunc/is_improvement_func.py
lclpy/aidfunc/logging.py
lclpy/aidfunc/pass_func.py
lclpy/benchmark/__init__.py
lclpy/benchmark/benchmark.py
lclpy/benchmark/statistics.py
lclpy/evaluation/__init__.py
lclpy/evaluation/abstract_evaluation_function.py
lclpy/evaluation/quadratic_assignment_evaluation_function.py
lclpy/evaluation/tsp_evaluation_function.py
lclpy/evaluation/deltaeval/__init__.py
lclpy/evaluation/deltaeval/delta_eval_func.py
lclpy/evaluation/deltaeval/delta_multi_neighbourhood.py
lclpy/evaluation/deltaeval/delta_qap.py
lclpy/evaluation/deltaeval/delta_tsp.py
lclpy/io/__init__.py
lclpy/io/csv_io.py
lclpy/io/qaplib.py
lclpy/io/tsplib.py
lclpy/localsearch/__init__.py
lclpy/localsearch/abstract_local_search.py
lclpy/localsearch/acceptance/__init__.py
lclpy/localsearch/acceptance/abstract_acceptance_function.py
lclpy/localsearch/acceptance/simulated_annealing_acceptance_function.py
lclpy/localsearch/move/__init__.py
lclpy/localsearch/move/abstract_move.py
lclpy/localsearch/move/array_reverse_order.py
lclpy/localsearch/move/array_swap.py
lclpy/localsearch/move/multi_neighbourhood.py
lclpy/localsearch/move/tsp_array_swap.py
lclpy/localsearch/simulatedannealing/__init__.py
lclpy/localsearch/simulatedannealing/abstr_iterations_temp_function.py
lclpy/localsearch/simulatedannealing/abstract_cooling_function.py
lclpy/localsearch/simulatedannealing/cnst_iterations_temp_function.py
lclpy/localsearch/simulatedannealing/geometric_cooling_function.py
lclpy/localsearch/simulatedannealing/simulated_annealing.py
lclpy/localsearch/steepestdescent/__init__.py
lclpy/localsearch/steepestdescent/steepest_descent.py
lclpy/localsearch/tabusearch/__init__.py
lclpy/localsearch/tabusearch/abstract_diff_state.py
lclpy/localsearch/tabusearch/sum_diff_state.py
lclpy/localsearch/tabusearch/tabu_list.py
lclpy/localsearch/tabusearch/tabu_search.py
lclpy-1.0.1.dist-info/LICENSE
lclpy-1.0.1.dist-info/METADATA
lclpy-1.0.1.dist-info/WHEEL
lclpy-1.0.1.dist-info/top_level.txt
lclpy-1.0.1.dist-info/RECORD
