Metadata-Version: 2.1
Name: lclpy
Version: 1.0.1
Summary: A localsearch library.
Home-page: https://github.com/nobody1570/lclpy
Author: Daan Thijs
Author-email: daan.thijs@hotmail.com
License: UNKNOWN
Platform: UNKNOWN
Classifier: Programming Language :: Python :: 3
Classifier: Operating System :: OS Independent
Classifier: License :: OSI Approved :: MIT License
Requires-Python: >=3.7
Requires-Dist: matplotlib (>=3.0.2)
Requires-Dist: numpy (>=1.15.4)
